client/__init__.py
client/client.py
client/client/__init__.py
client/client/add_contact.py
client/client/database.py
client/client/del_contact.py
client/client/main_window.py
client/client/main_window_conv.py
client/client/start_dialog.py
client/client/transport.py
client/common/__init__.py
client/common/decorated.py
client/common/descriptrs.py
client/common/errors.py
client/common/metaclasses.py
client/common/utils.py
client/common/variables.py
client/doc/__init__.py
client/doc/source/__init__.py
client/doc/source/conf.py
client/logs/__init__.py
client/logs/config_client_log.py
client/unit_tests/__init__.py
client/unit_tests/test_client.py
client/unit_tests/test_server.py
client/unit_tests/test_utils.py
py_messag_client-0.1.0.dist-info/METADATA
py_messag_client-0.1.0.dist-info/WHEEL
py_messag_client-0.1.0.dist-info/top_level.txt
py_messag_client-0.1.0.dist-info/RECORD
